sec_certs/__init__.py
sec_certs/__main__.py
sec_certs/_version.py
sec_certs/cert_rules.py
sec_certs/cli.py
sec_certs/configuration.py
sec_certs/constants.py
sec_certs/rules.yaml
sec_certs/data/readme.md
sec_certs/data/cert_ids/duplicate_ids.csv
sec_certs/data/cert_ids/missing_ids.csv
sec_certs/data/cert_ids/random.csv
sec_certs/data/cert_ids/readme.md
sec_certs/data/cert_ids/truth.csv
sec_certs/data/cpes/label_studio_interface.txt
sec_certs/data/cpes/manual_cpe_labels.json
sec_certs/data/cpes/random.csv
sec_certs/data/cpes/readme.md
sec_certs/data/cpes/outdated/cc.json
sec_certs/data/cpes/outdated/fips.json
sec_certs/data/cpes/validation_test_split/cc/test.json
sec_certs/data/cpes/validation_test_split/cc/validation.json
sec_certs/data/cpes/validation_test_split/fips/test.json
sec_certs/data/cpes/validation_test_split/fips/validation.json
sec_certs/data/information_retrieval/split/metadata.csv
sec_certs/data/information_retrieval/split/sampled_images.json
sec_certs/data/information_retrieval/split/test.json
sec_certs/data/information_retrieval/split/train.json
sec_certs/data/information_retrieval/split/valid.json
sec_certs/data/reference_annotations/outdated_manually_annotated_references.csv
sec_certs/data/reference_annotations/readme.md
sec_certs/data/reference_annotations/adam/test.csv
sec_certs/data/reference_annotations/adam/train.csv
sec_certs/data/reference_annotations/adam/valid.csv
sec_certs/data/reference_annotations/conflicts/test.csv
sec_certs/data/reference_annotations/conflicts/train.csv
sec_certs/data/reference_annotations/conflicts/valid.csv
sec_certs/data/reference_annotations/final/test.csv
sec_certs/data/reference_annotations/final/train.csv
sec_certs/data/reference_annotations/final/valid.csv
sec_certs/data/reference_annotations/jano/test.csv
sec_certs/data/reference_annotations/jano/train.csv
sec_certs/data/reference_annotations/jano/valid.csv
sec_certs/data/reference_annotations/split/test.json
sec_certs-0.2.1.dist-info/LICENSE
sec_certs-0.2.1.dist-info/METADATA
sec_certs-0.2.1.dist-info/WHEEL
sec_certs-0.2.1.dist-info/entry_points.txt
sec_certs-0.2.1.dist-info/top_level.txt
sec_certs-0.2.1.dist-info/RECORD
