Metadata-Version: 2.1
Name: sec-certs
Version: 0.2.1
Summary: A tool for data scraping and analysis of security certificates from Common Criteria and FIPS 140-2/3 frameworks
Author: Jan Jancar, Petr Svenda, Jiri Michalik, Stanislav Bobon
Author-email: Adam Janovsky <adamjanovsky@mail.muni.cz>
License: MIT
Project-URL: Homepage, https://seccerts.org
Project-URL: GitHub, https://github.com/crocs-muni/sec-certs/
Project-URL: Documentation, https://seccerts.org/docs
Classifier: Development Status :: 3 - Alpha
Classifier: License :: OSI Approved :: MIT License
Classifier: Topic :: Security
Classifier: Topic :: Security :: Cryptography
Classifier: Programming Language :: Python :: 3.10
Classifier: Programming Language :: Python :: 3.11
Classifier: Intended Audience :: Developers
Classifier: Intended Audience :: Science/Research
Requires-Python: >=3.10
License-File: LICENSE
Requires-Dist: beautifulsoup4
Requires-Dist: click
Requires-Dist: html5lib
Requires-Dist: jsonschema
Requires-Dist: lxml
Requires-Dist: matplotlib
Requires-Dist: numpy
Requires-Dist: pandas
Requires-Dist: pdftotext
Requires-Dist: pikepdf
Requires-Dist: Pillow >=9.2.0
Requires-Dist: pypdf[crypto] >=3.1.0
Requires-Dist: python-dateutil
Requires-Dist: PyYAML
Requires-Dist: rapidfuzz
Requires-Dist: requests
Requires-Dist: scikit-learn
Requires-Dist: tabula-py
Requires-Dist: tqdm
Requires-Dist: setuptools-scm
Requires-Dist: ipykernel
Requires-Dist: ipywidgets
Requires-Dist: spacy
Requires-Dist: pkgconfig
Requires-Dist: seaborn
Requires-Dist: pySankeyBeta
Requires-Dist: scipy >=1.9.0
Requires-Dist: networkx
Requires-Dist: pydantic
Requires-Dist: pydantic-settings
Requires-Dist: psutil
Requires-Dist: pytesseract
Provides-Extra: dev
Requires-Dist: ruff ==0.2.2 ; extra == 'dev'
Requires-Dist: mypy ==1.8.0 ; extra == 'dev'
Requires-Dist: types-PyYAML ; extra == 'dev'
Requires-Dist: types-python-dateutil ; extra == 'dev'
Requires-Dist: types-requests ; extra == 'dev'
Requires-Dist: datasets ; extra == 'dev'
Requires-Dist: pytest ; extra == 'dev'
Requires-Dist: pytest-cov ; extra == 'dev'
Requires-Dist: pytest-monitor ; extra == 'dev'
Requires-Dist: pytest-profiling ; extra == 'dev'
Requires-Dist: pre-commit ; extra == 'dev'
Requires-Dist: pip-tools ; extra == 'dev'
Requires-Dist: sphinx ; extra == 'dev'
Requires-Dist: myst-nb >=0.14 ; extra == 'dev'
Requires-Dist: sphinx-book-theme ; extra == 'dev'
Requires-Dist: sphinx-design ; extra == 'dev'
Requires-Dist: sphinx-copybutton ; extra == 'dev'
Requires-Dist: ipython !=8.7.0 ; extra == 'dev'
Provides-Extra: nlp
Requires-Dist: catboost ; extra == 'nlp'
Requires-Dist: optuna ; extra == 'nlp'
Requires-Dist: setfit ; extra == 'nlp'
Requires-Dist: umap-learn[plot] ; extra == 'nlp'
Requires-Dist: plotly ; extra == 'nlp'
Requires-Dist: scikit-learn ; extra == 'nlp'
Provides-Extra: test
Requires-Dist: pytest ; extra == 'test'
Requires-Dist: coverage ; extra == 'test'
Requires-Dist: pytest-cov ; extra == 'test'
